regressionmadesimple/__init__.py
regressionmadesimple/base_class.py
regressionmadesimple/cubic.py
regressionmadesimple/curves.py
regressionmadesimple/linear.py
regressionmadesimple/options.py
regressionmadesimple/quadratic.py
regressionmadesimple/utils_preworks.py
regressionmadesimple/wrapper.py
regressionmadesimple/models/__init__.py
regressionmadesimple/models/base.py
regressionmadesimple/models/cubic.py
regressionmadesimple/models/curves.py
regressionmadesimple/models/linear.py
regressionmadesimple/models/quadratic.py
regressionmadesimple-3.0.0.dist-info/licenses/LICENSE
regressionmadesimple-3.0.0.dist-info/METADATA
regressionmadesimple-3.0.0.dist-info/WHEEL
regressionmadesimple-3.0.0.dist-info/top_level.txt
regressionmadesimple-3.0.0.dist-info/RECORD
