Metadata-Version: 2.4
Name: regressionmadesimple
Version: 3.0.0
Summary: Minimalist machine learning toolkit that wraps `scikit-learn` for quick prototyping. Just `import rms` and go.
Home-page: https://github.com/Unknownuserfrommars/regressionmadesimple
Author: Unknownuserfrommars
License: MIT
Keywords: machine-learning regression sklearn wrapper polynomial curve-fitting
Classifier: Programming Language :: Python :: 3
Classifier: License :: OSI Approved :: MIT License
Classifier: Operating System :: OS Independent
Classifier: Intended Audience :: Developers
Classifier: Topic :: Scientific/Engineering
Classifier: Development Status :: 4 - Beta
Requires-Python: >=3.10
License-File: LICENSE
Requires-Dist: pandas
Requires-Dist: numpy
Requires-Dist: plotly
Requires-Dist: scikit-learn
Requires-Dist: matplotlib
Requires-Dist: joblib
Dynamic: author
Dynamic: classifier
Dynamic: description
Dynamic: description-content-type
Dynamic: home-page
Dynamic: keywords
Dynamic: license
Dynamic: license-file
Dynamic: requires-dist
Dynamic: requires-python
Dynamic: summary
